README.rst
setup.py
ttp/__init__.py
ttp/tests.py
ttp/ttp.py
ttp/utils.py
twitter_text_python.egg-info/PKG-INFO
twitter_text_python.egg-info/SOURCES.txt
twitter_text_python.egg-info/dependency_links.txt
twitter_text_python.egg-info/not-zip-safe
twitter_text_python.egg-info/top_level.txt