Metadata-Version: 1.1
Name: twitter-text-python
Version: 1.0.3
Summary: Twitter Tweet parser and formatter
Home-page: https://github.com/edburnett/twitter-text-python
Author: Maintained by Edmond Burnett (originally Ivo Wetzel)
Author-email: _@edmondburnett.com
License: MIT
Platform: UNKNOWN
Classifier: Environment :: Console
Classifier: Intended Audience :: Developers
Classifier: License :: OSI Approved :: MIT License
Classifier: Operating System :: OS Independent
Classifier: Programming Language :: Python
Classifier: Topic :: Software Development :: Libraries :: Python Modules
Classifier: Topic :: Text Processing :: Linguistic
